blockspring/__init__.py
blockspring/__version__.py
blockspring/api.py
blockspring/models.py
blockspring-0.1.13.dist-info/DESCRIPTION.rst
blockspring-0.1.13.dist-info/METADATA
blockspring-0.1.13.dist-info/metadata.json
blockspring-0.1.13.dist-info/RECORD
blockspring-0.1.13.dist-info/top_level.txt
blockspring-0.1.13.dist-info/WHEEL
