Metadata-Version: 1.1
Name: blockspring
Version: 0.1.13
Summary: Blockspring api wrapper
Home-page: https://www.blockspring.com
Author: Blockspring
Author-email: paul@blockspring.com
License: MIT
Keywords: blockspring function cloud api service library development
Platform: UNKNOWN
Classifier: Development Status :: 5 - Production/Stable
Classifier: Intended Audience :: Developers
Classifier: Topic :: Software Development :: Build Tools
Classifier: License :: OSI Approved :: MIT License
Classifier: Programming Language :: Python :: 2
Classifier: Programming Language :: Python :: 2.6
Classifier: Programming Language :: Python :: 2.7
Classifier: Programming Language :: Python :: 3
Classifier: Programming Language :: Python :: 3.2
Classifier: Programming Language :: Python :: 3.3
Classifier: Programming Language :: Python :: 3.4
